ultrachronic/__init__.py
ultrachronic/_version.py
ultrachronic/ultrachronic.py
ultrachronic-0.1.5.dist-info/DESCRIPTION.rst
ultrachronic-0.1.5.dist-info/METADATA
ultrachronic-0.1.5.dist-info/RECORD
ultrachronic-0.1.5.dist-info/WHEEL
ultrachronic-0.1.5.dist-info/metadata.json
ultrachronic-0.1.5.dist-info/top_level.txt
