Metadata-Version: 2.0
Name: ultrachronic
Version: 0.1.5
Summary: Run parallel jobs and save results to json.gz files
Home-page: https://github.com/yoavram/ultrachronic
Author: Yoav Ram
Author-email: yoav@yoavram.com
License: MIT
Platform: UNKNOWN
Classifier: Development Status :: 4 - Beta
Classifier: Intended Audience :: Developers
Classifier: Topic :: Software Development :: User Interfaces
Classifier: License :: OSI Approved :: MIT License
Classifier: Programming Language :: Python :: 3.4
Classifier: Programming Language :: Python :: 3.5
Classifier: Programming Language :: Python :: 3.6
Provides-Extra: dist
Requires-Dist: requests; extra == 'dist'
Provides-Extra: test
Requires-Dist: click (>=5); extra == 'test'
Requires-Dist: nose; extra == 'test'
